gtdownloader/__init__.py
gtdownloader/apicall.py
gtdownloader/downloader.py
gtdownloader/geomethods.py
gtdownloader/py.typed
gtdownloader/_utils/__init__.py
gtdownloader/_utils/utils.py
gtdownloader-1.0.1.dist-info/LICENSE.txt
gtdownloader-1.0.1.dist-info/METADATA
gtdownloader-1.0.1.dist-info/WHEEL
gtdownloader-1.0.1.dist-info/top_level.txt
gtdownloader-1.0.1.dist-info/RECORD
