Metadata-Version: 2.1
Name: gtdownloader
Version: 1.0.1
Summary: A Python package for the simple downloading of tweets with geographical information
Home-page: https://gtdownloader.readthedocs.io/
Author: Juan G Acosta
Author-email: jgacostas@icloud.com
License: MIT
Classifier: Intended Audience :: Developers
Classifier: License :: OSI Approved :: MIT License
Classifier: Programming Language :: Python
Classifier: Programming Language :: Python :: 3
Classifier: Programming Language :: Python :: 3.6
Classifier: Programming Language :: Python :: 3.7
Classifier: Programming Language :: Python :: 3.8
Classifier: Programming Language :: Python :: 3.9
Classifier: Operating System :: OS Independent
License-File: LICENSE.txt
Requires-Dist: requests
Requires-Dist: pandas (>=1.3.2)
Requires-Dist: geopandas (>=0.10.2)
Requires-Dist: matplotlib (>=3.4.3)
Requires-Dist: seaborn (>=0.11.2)
Requires-Dist: shapely (>=1.8.0)
Requires-Dist: wordcloud (>=1.8.2.2)
Requires-Dist: plotly (>=5.5.0)
Requires-Dist: pyyaml
Provides-Extra: testing
Requires-Dist: pytest (>=7.0) ; extra == 'testing'
Requires-Dist: pytest-cov (>=2.0) ; extra == 'testing'
Requires-Dist: mypy (>=0.910) ; extra == 'testing'
Requires-Dist: flake8 (>=3.9) ; extra == 'testing'
Requires-Dist: tox (>=3.24) ; extra == 'testing'
